pyMixtComp/MixtComp.py
pyMixtComp/__init__.py
pyMixtComp/_version.py
pyMixtComp/pyMixtCompBridge.so
pyMixtComp/bridge/__init__.py
pyMixtComp/bridge/bridge.py
pyMixtComp/bridge/convert.py
pyMixtComp/bridge/utils.py
pyMixtComp/data/__init__.py
pyMixtComp/data/canadian_weather.csv
pyMixtComp/data/candy.csv
pyMixtComp/data/data.py
pyMixtComp/data/drug200.csv
pyMixtComp/data/housing.csv
pyMixtComp/data/iris.csv
pyMixtComp/data/mushrooms.csv
pyMixtComp/data/prostate.csv
pyMixtComp/data/purchasing_behaviour.csv
pyMixtComp/data/simulated_data.csv
pyMixtComp/data/stars.csv
pyMixtComp/data/titanic.csv
pyMixtComp/data/titanic_clean.csv
pyMixtComp/data/wine.csv
pyMixtComp/plot/__init__.py
pyMixtComp/plot/barplot.py
pyMixtComp/plot/confusion_matrix.py
pyMixtComp/plot/functional.py
pyMixtComp/plot/heatmap.py
pyMixtComp/plot/univariate_boxplot.py
pyMixtComp/plot/univariate_distribution.py
pyMixtComp/utils/__init__.py
pyMixtComp/utils/convert.py
pyMixtComp/utils/criterion.py
pyMixtComp/utils/getter.py
pyMixtComp/utils/label_encoding.py
pyMixtComp/utils/lg_summary.py
pyMixtComp/utils/sample.py
pyMixtComp/utils/slicer.py
tests/__init__.py
tests/test_MixtComp.py
tests/test_bridge_convert.py
tests/test_bridge_utils.py
tests/test_data.py
tests/test_plot.py
tests/test_utils_convert.py
tests/test_utils_getter.py
tests/test_utils_sample.py
pyMixtComp-2.2.1.dist-info/METADATA
pyMixtComp-2.2.1.dist-info/WHEEL
pyMixtComp-2.2.1.dist-info/top_level.txt
pyMixtComp-2.2.1.dist-info/RECORD
